nwc_safer/__init__.py
nwc_safer/__main__.py
nwc_safer/cli.py
nwc_safer/filehandler.py
nwc_safer/processor.py
nwc_safer/product.py
nwc_safer/watcher.py
nwc_safer-0.8.0.dist-info/entry_points.txt
nwc_safer-0.8.0.dist-info/LICENSE.md
nwc_safer-0.8.0.dist-info/METADATA
nwc_safer-0.8.0.dist-info/WHEEL
nwc_safer-0.8.0.dist-info/RECORD
