Metadata-Version: 2.1
Name: nwc-safer
Version: 0.8.0
Summary: NWC-SAFer CLI tool simplifying NetCDF data extraction and conversion of NWC-SAF products.
Home-page: https://github.com/fotioudim/NWC-SAFer
License: MIT
Keywords: nwc-saf,netcdf,typer,python,poetry,watchdog
Author: dfotiou
Author-email: fotioudimitris93@vodafone.com
Requires-Python: >=3.10,<4.0
Classifier: License :: OSI Approved :: MIT License
Classifier: Programming Language :: Python :: 3
Classifier: Programming Language :: Python :: 3.10
Classifier: Programming Language :: Python :: 3.11
Classifier: Topic :: Scientific/Engineering :: Image Processing
Classifier: Topic :: Software Development :: Libraries :: Python Modules
Requires-Dist: dask (>=2023.3.1,<2024.0.0)
Requires-Dist: netcdf4 (>=1.6.3,<2.0.0)
Requires-Dist: openpyxl (>=3.1.2,<4.0.0)
Requires-Dist: setuptools (>=67.6.0,<68.0.0)
Requires-Dist: typer[all] (>=0.7.0,<0.8.0)
Requires-Dist: watchdog (>=2.3.1,<3.0.0)
Requires-Dist: xarray (>=2023.2.0,<2024.0.0)
Project-URL: Repository, https://github.com/fotioudim/NWC-SAFer
